mcp_server_generator/__init__.py
mcp_server_generator/main.py
mcp_server_generator-0.1.0.dist-info/METADATA
mcp_server_generator-0.1.0.dist-info/WHEEL
mcp_server_generator-0.1.0.dist-info/top_level.txt
mcp_server_generator-0.1.0.dist-info/RECORD
